setup.py
textgears/__init__.py
textgears.egg-info/PKG-INFO
textgears.egg-info/SOURCES.txt
textgears.egg-info/dependency_links.txt
textgears.egg-info/requires.txt
textgears.egg-info/top_level.txt